LICENSE
ncomix/__init__.py
ncomix/__main__.py
ncomix/ncomix.py
ncomix-0.1.2.dist-info/LICENSE
ncomix-0.1.2.dist-info/WHEEL
ncomix-0.1.2.dist-info/METADATA
ncomix-0.1.2.dist-info/RECORD
